pytech/rules/__init__.py
pytech/rules/conversions.py
pytech/rules/rules.py
pytech_rules-2.2.4.dist-info/METADATA
pytech_rules-2.2.4.dist-info/WHEEL
pytech_rules-2.2.4.dist-info/licenses/LICENCE
pytech_rules-2.2.4.dist-info/RECORD
