Metadata-Version: 2.4
Name: pytech-rules
Version: 2.2.4
Summary: PyTech Rules Project
Project-URL: Homepage, https://gitlab.com/pytech-srl/resources/pytech-rules/
Project-URL: Bug Tracker, https://gitlab.com/pytech-srl/resources/pytech-rules/-/issues
Project-URL: Documentation, https://pytech-srl.gitlab.io/resources/pytech-rules/
Author: Giacomo Nicolini, Alessandra Benassi
Author-email: Alessandro Grandi <alessandro.grandi@pytech.it>
License-File: LICENCE
Classifier: License :: OSI Approved :: GNU Affero General Public License v3 or later (AGPLv3+)
Classifier: Operating System :: OS Independent
Classifier: Programming Language :: Python
Classifier: Programming Language :: Python :: 3
Requires-Python: >=3
